README.rst
setup.cfg
setup.py
mika/__init__.py
mika/ir/__init__.py
mika/ir/search.py
mika/kd/FMEA.py
mika/kd/NER.py
mika/kd/__init__.py
mika/kd/topic_model_plus.py
mika/kd/trend_analysis.py
mika/utils/Data.py
mika/utils/ICS.py
mika/utils/LLIS.py
mika/utils/SAFECOM.py
mika/utils/SAFENET.py
mika/utils/__init__.py
mika/utils/safecom_webscraper.py
nasa_mika.egg-info/PKG-INFO
nasa_mika.egg-info/SOURCES.txt
nasa_mika.egg-info/dependency_links.txt
nasa_mika.egg-info/requires.txt
nasa_mika.egg-info/top_level.txt
test/test_Data.py
test/test_FMEA.py
test/test_NER.py
test/test_identify_docs_per_hazard.py