Metadata-Version: 2.1
Name: nasa-mika
Version: 1.0.3
Summary: Manager for Intelligent Knowledge Access (MIKA)
Home-page: https://github.com/nasa/mika.git
Download-URL: https://github.com/nasa/mika/archive/refs/tags/v1.0.3.tar.gz
Author: Hannah Walsh and Sequoia Andrade
Author-email: hannah.s.walsh@nasa.gov
Maintainer: sequoiarose
Maintainer-email: sequoia.r.andrade@nasa.gov
Project-URL: Documentation, https://nasa.github.io/mika/
Keywords: Natural Language Processing,Knowledge Management,Topic Modeling
Classifier: Programming Language :: Python :: 3
Classifier: License :: OSI Approved
Classifier: Development Status :: 3 - Alpha
Requires-Python: >=3.8
